<annotation verified="yes">
    <folder>Annotation</folder>
    <filename>42.png</filename>
    <path>dent-PascalVOC-export/Annotations/42.png</path>
    <source>
        <database>Unknown</database>
    </source>
    <size>
        <width>3000</width>
        <height>1250</height>
        <depth>3</depth>
    </size>
    <segmented>0</segmented>
    <object>
    <name>11</name>
    <pose>Unspecified</pose>
    <truncated>0</truncated>
    <difficult>0</difficult>
    <bndbox>
        <xmin>1321.654895510836</xmin>
        <ymin>205.58574412128712</ymin>
        <xmax>1461.699400154799</xmax>
        <ymax>577.0904238861386</ymax>
    </bndbox>
</object><object>
    <name>12</name>
    <pose>Unspecified</pose>
    <truncated>0</truncated>
    <difficult>0</difficult>
    <bndbox>
        <xmin>1218.048568111455</xmin>
        <ymin>185.81277073019803</ymin>
        <xmax>1338.12645123839</xmax>
        <ymax>564.7141862623763</ymax>
    </bndbox>
</object><object>
    <name>13</name>
    <pose>Unspecified</pose>
    <truncated>0</truncated>
    <difficult>0</difficult>
    <bndbox>
        <xmin>1111.1769543343653</xmin>
        <ymin>125.86536974009901</ymin>
        <xmax>1223.1037151702785</xmax>
        <ymax>588.37890625</ymax>
    </bndbox>
</object><object>
    <name>14</name>
    <pose>Unspecified</pose>
    <truncated>0</truncated>
    <difficult>0</difficult>
    <bndbox>
        <xmin>997.9803599071208</xmin>
        <ymin>235.77699566831683</ymin>
        <xmax>1120.295568885449</xmax>
        <ymax>573.4524868502475</ymax>
    </bndbox>
</object><object>
    <name>15</name>
    <pose>Unspecified</pose>
    <truncated>0</truncated>
    <difficult>0</difficult>
    <bndbox>
        <xmin>811.859036377709</xmin>
        <ymin>249.1926438737624</ymin>
        <xmax>991.6432856037152</xmax>
        <ymax>562.6957959467823</ymax>
    </bndbox>
</object><object>
    <name>16</name>
    <pose>Unspecified</pose>
    <truncated>0</truncated>
    <difficult>0</difficult>
    <bndbox>
        <xmin>665.3807082043344</xmin>
        <ymin>261.1216932240099</ymin>
        <xmax>841.5489551083592</xmax>
        <ymax>562.3090385210396</ymax>
    </bndbox>
</object><object>
    <name>17</name>
    <pose>Unspecified</pose>
    <truncated>0</truncated>
    <difficult>0</difficult>
    <bndbox>
        <xmin>507.76412538699697</xmin>
        <ymin>274.2110148514852</ymin>
        <xmax>694.3208204334367</xmax>
        <ymax>547.2134127475248</ymax>
    </bndbox>
</object><object>
    <name>31</name>
    <pose>Unspecified</pose>
    <truncated>0</truncated>
    <difficult>0</difficult>
    <bndbox>
        <xmin>1503.2048181114553</xmin>
        <ymin>605.35997447401</ymin>
        <xmax>1577.3026315789475</xmax>
        <ymax>962.2162167388615</ymax>
    </bndbox>
</object><object>
    <name>32</name>
    <pose>Unspecified</pose>
    <truncated>0</truncated>
    <difficult>0</difficult>
    <bndbox>
        <xmin>1582.3819659442725</xmin>
        <ymin>607.2091584158416</ymin>
        <xmax>1674.922600619195</xmax>
        <ymax>962.5425433168318</ymax>
    </bndbox>
</object><object>
    <name>33</name>
    <pose>Unspecified</pose>
    <truncated>0</truncated>
    <difficult>0</difficult>
    <bndbox>
        <xmin>1667.4970975232202</xmin>
        <ymin>611.439317759901</ymin>
        <xmax>1777.0897832817338</xmax>
        <ymax>980.0070583230198</ymax>
    </bndbox>
</object><object>
    <name>34</name>
    <pose>Unspecified</pose>
    <truncated>0</truncated>
    <difficult>0</difficult>
    <bndbox>
        <xmin>1768.1404798761612</xmin>
        <ymin>609.4571859529703</ymin>
        <xmax>1883.7195239938083</xmax>
        <ymax>950.3475982363861</ymax>
    </bndbox>
</object><object>
    <name>35</name>
    <pose>Unspecified</pose>
    <truncated>0</truncated>
    <difficult>0</difficult>
    <bndbox>
        <xmin>1878.7248452012386</xmin>
        <ymin>612.4062113242575</ymin>
        <xmax>2008.1874032507742</xmax>
        <ymax>949.4653078589109</ymax>
    </bndbox>
</object><object>
    <name>37</name>
    <pose>Unspecified</pose>
    <truncated>0</truncated>
    <difficult>0</difficult>
    <bndbox>
        <xmin>2122.702205882353</xmin>
        <ymin>581.6710821472773</ymin>
        <xmax>2350.111261609907</xmax>
        <ymax>889.78380259901</ymax>
    </bndbox>
</object><object>
    <name>38</name>
    <pose>Unspecified</pose>
    <truncated>0</truncated>
    <difficult>0</difficult>
    <bndbox>
        <xmin>2310.5529218266256</xmin>
        <ymin>549.7515083539604</ymin>
        <xmax>2487.616099071208</xmax>
        <ymax>814.6561726485148</ymax>
    </bndbox>
</object><object>
    <name>41</name>
    <pose>Unspecified</pose>
    <truncated>0</truncated>
    <difficult>0</difficult>
    <bndbox>
        <xmin>1407.0965557275542</xmin>
        <ymin>600.7672300433169</ymin>
        <xmax>1491.7279411764707</xmax>
        <ymax>906.8011293316832</ymax>
    </bndbox>
</object><object>
    <name>42</name>
    <pose>Unspecified</pose>
    <truncated>0</truncated>
    <difficult>0</difficult>
    <bndbox>
        <xmin>1326.5286377708978</xmin>
        <ymin>603.4382735148515</ymin>
        <xmax>1411.220491486068</xmax>
        <ymax>927.7102026608911</ymax>
    </bndbox>
</object><object>
    <name>43</name>
    <pose>Unspecified</pose>
    <truncated>0</truncated>
    <difficult>0</difficult>
    <bndbox>
        <xmin>1215.0130611455108</xmin>
        <ymin>601.939588490099</ymin>
        <xmax>1324.920181888545</xmax>
        <ymax>976.6471031868812</ymax>
    </bndbox>
</object><object>
    <name>44</name>
    <pose>Unspecified</pose>
    <truncated>0</truncated>
    <difficult>0</difficult>
    <bndbox>
        <xmin>1109.2056888544892</xmin>
        <ymin>618.9690013923267</ymin>
        <xmax>1220.1649574303406</xmax>
        <ymax>957.2246287128713</ymax>
    </bndbox>
</object><object>
    <name>45</name>
    <pose>Unspecified</pose>
    <truncated>0</truncated>
    <difficult>0</difficult>
    <bndbox>
        <xmin>993.046149380805</xmin>
        <ymin>612.3820389851485</ymin>
        <xmax>1111.418827399381</xmax>
        <ymax>956.2335628094058</ymax>
    </bndbox>
</object><object>
    <name>46</name>
    <pose>Unspecified</pose>
    <truncated>0</truncated>
    <difficult>0</difficult>
    <bndbox>
        <xmin>806.0540828173375</xmin>
        <ymin>600.2716970915842</ymin>
        <xmax>1004.7528057275542</xmax>
        <ymax>948.5588451423268</ymax>
    </bndbox>
</object><object>
    <name>47</name>
    <pose>Unspecified</pose>
    <truncated>0</truncated>
    <difficult>0</difficult>
    <bndbox>
        <xmin>624.733939628483</xmin>
        <ymin>582.2995629641089</ymin>
        <xmax>839.4446594427245</xmax>
        <ymax>901.9183168316831</ymax>
    </bndbox>
</object><object>
    <name>48</name>
    <pose>Unspecified</pose>
    <truncated>0</truncated>
    <difficult>0</difficult>
    <bndbox>
        <xmin>462.42501934984523</xmin>
        <ymin>564.6658415841584</ymin>
        <xmax>673.7374226006192</xmax>
        <ymax>853.1506226794554</ymax>
    </bndbox>
</object><object>
    <name>21</name>
    <pose>Unspecified</pose>
    <truncated>0</truncated>
    <difficult>0</difficult>
    <bndbox>
        <xmin>1458.3010835913315</xmin>
        <ymin>194.46646813118812</ymin>
        <xmax>1600.4015092879258</xmax>
        <ymax>584.7772277227723</ymax>
    </bndbox>
</object><object>
    <name>22</name>
    <pose>Unspecified</pose>
    <truncated>0</truncated>
    <difficult>0</difficult>
    <bndbox>
        <xmin>1603.2556114551085</xmin>
        <ymin>176.92943610767327</ymin>
        <xmax>1721.108262383901</xmax>
        <ymax>586.203395730198</ymax>
    </bndbox>
</object><object>
    <name>23</name>
    <pose>Unspecified</pose>
    <truncated>0</truncated>
    <difficult>0</difficult>
    <bndbox>
        <xmin>1724.4582043343655</xmin>
        <ymin>149.61469291460398</ymin>
        <xmax>1829.8785797213627</xmax>
        <ymax>590.9290880259902</ymax>
    </bndbox>
</object><object>
    <name>24</name>
    <pose>Unspecified</pose>
    <truncated>0</truncated>
    <difficult>0</difficult>
    <bndbox>
        <xmin>1820.8809017027866</xmin>
        <ymin>171.8169863861386</ymin>
        <xmax>1931.5741099071208</xmax>
        <ymax>582.1907874381188</ymax>
    </bndbox>
</object><object>
    <name>25</name>
    <pose>Unspecified</pose>
    <truncated>0</truncated>
    <difficult>0</difficult>
    <bndbox>
        <xmin>1922.1047794117649</xmin>
        <ymin>177.2799350247525</ymin>
        <xmax>2046.0889125386998</xmax>
        <ymax>579.435140779703</ymax>
    </bndbox>
</object><object>
    <name>27</name>
    <pose>Unspecified</pose>
    <truncated>0</truncated>
    <difficult>0</difficult>
    <bndbox>
        <xmin>2188.467492260062</xmin>
        <ymin>218.84427212252476</ymin>
        <xmax>2360.1610874613007</xmax>
        <ymax>570.7451848700496</ymax>
    </bndbox>
</object>
</annotation>
